
  [
    {
      "text": "Rahul ko 500 ka bill bana do",
    "intent": "Create_Invoice",
    "entities": [
      {"entity": "CUSTOMER_NAME", "value": "Rahul"},
      {"entity": "AMOUNT", "value": "500"}
    ]
  },
  {
    "text": "Neha ke liye 1200 ka invoice generate karo",
    "intent": "Create_Invoice",
    "entities": [
      {"entity": "CUSTOMER_NAME", "value": "Neha"},
      {"entity": "AMOUNT", "value": "1200"}
    ]
  },
  {
    "text": "Generate invoice for Mohan 1200",
    "intent": "Create_Invoice",
    "entities": [
      {"entity": "CUSTOMER_NAME", "value": "Mohan"},
      {"entity": "AMOUNT", "value": "1200"}
    ]
  },
  {
    "text": "3000 ka maal diya Sharma ji ko",
    "intent": "Create_Invoice",
    "entities": [
      {"entity": "AMOUNT", "value": "3000"},
      {"entity": "CUSTOMER_NAME", "value": "Sharma ji"}
    ]
  },
  {
    "text": "Bill bana do 800 ka",
    "intent": "Create_Invoice",
    "entities": [
      {"entity": "AMOUNT", "value": "800"}
    ]
  },
  {
    "text": "1200 ka bill bana do Ramesh ke naam pe",
    "intent": "Create_Invoice",
    "entities": [
      {"entity": "AMOUNT", "value": "1200"},
      {"entity": "CUSTOMER_NAME", "value": "Ramesh"}
    ]
  },
  {
    "text": "Sohan ko 750 ka invoice bhejna hai",
    "intent": "Create_Invoice",
    "entities": [
      {"entity": "CUSTOMER_NAME", "value": "Sohan"},
      {"entity": "AMOUNT", "value": "750"}
    ]
  },
  {
    "text": "2 hazar ka maal diya tha Amit ko bill bana do",
    "intent": "Create_Invoice",
    "entities": [
      {"entity": "AMOUNT", "value": "2000"},
      {"entity": "CUSTOMER_NAME", "value": "Amit"}
    ]
  },
  {
    "text": "Invoice bana 450 ka Ankit ke liye",
    "intent": "Create_Invoice",
    "entities": [
      {"entity": "AMOUNT", "value": "450"},
      {"entity": "CUSTOMER_NAME", "value": "Ankit"}
    ]
  },
  {
    "text": "Kal jo 900 ka saman diya tha uska bill generate karo",
    "intent": "Create_Invoice",
    "entities": [
      {"entity": "AMOUNT", "value": "900"},
      {"entity": "DATE_REFERENCE", "value": "kal"}
    ]
  },
  {
    "text": "1800 ka bill create kar de Gupta ji ke naam se",
    "intent": "Create_Invoice",
    "entities": [
      {"entity": "AMOUNT", "value": "1800"},
      {"entity": "CUSTOMER_NAME", "value": "Gupta ji"}
    ]
  },
  {
    "text": "650 ka bill bana aur bhej bhi dena",
    "intent": "Create_Invoice",
    "entities": [
      {"entity": "AMOUNT", "value": "650"}
    ]
  },
  {
    "text": "Mohit ko 3 hazar ka maal gaya invoice bana",
    "intent": "Create_Invoice",
    "entities": [
      {"entity": "CUSTOMER_NAME", "value": "Mohit"},
      {"entity": "AMOUNT", "value": "3000"}
    ]
  },
  {
    "text": "2500 ka invoice bana do kal ki date se",
    "intent": "Create_Invoice",
    "entities": [
      {"entity": "AMOUNT", "value": "2500"},
      {"entity": "DATE_REFERENCE", "value": "kal"}
    ]
  },
  {
    "text": "999 ka bill bana do customer Ravi",
    "intent": "Create_Invoice",
    "entities": [
      {"entity": "AMOUNT", "value": "999"},
      {"entity": "CUSTOMER_NAME", "value": "Ravi"}
    ]
  },
  {
    "text": "500 ka bana do bill Rahul",
    "intent": "Create_Invoice",
    "entities": [
      {"entity": "AMOUNT", "value": "500"},
      {"entity": "CUSTOMER_NAME", "value": "Rahul"}
    ]
  },
  {
    "text": "bill 1400 ka Suresh",
    "intent": "Create_Invoice",
    "entities": [
      {"entity": "AMOUNT", "value": "1400"},
      {"entity": "CUSTOMER_NAME", "value": "Suresh"}
    ]
  },
  {
    "text": "2100 ka maal gaya Sharma ji invoice",
    "intent": "Create_Invoice",
    "entities": [
      {"entity": "AMOUNT", "value": "2100"},
      {"entity": "CUSTOMER_NAME", "value": "Sharma ji"}
    ]
  },
  {
    "text": "kal 800 diya tha uska bill",
    "intent": "Create_Invoice",
    "entities": [
      {"entity": "AMOUNT", "value": "800"},
      {"entity": "DATE_REFERENCE", "value": "kal"}
    ]
  },
  {
    "text": "3000 ka bana do uske naam pe",
    "intent": "Create_Invoice",
    "entities": [
      {"entity": "AMOUNT", "value": "3000"}
    ]
  },
  {
    "text": "Sharma ji ke naam pe ek naya bill bana",
    "intent": "Create_Invoice",
    "entities": [
      {"entity": "CUSTOMER_NAME", "value": "Sharma ji"}
    ]
  },
  {
    "text": "Aaj ka 1450 ka invoice bana do Deepak ke liye",
    "intent": "Create_Invoice",
    "entities": [
      {"entity": "DATE_REFERENCE", "value": "aaj"},
      {"entity": "AMOUNT", "value": "1450"},
      {"entity": "CUSTOMER_NAME", "value": "Deepak"}
    ]
  },
  {
    "text": "4 packet diya tha Raju ko uska bill bana",
    "intent": "Create_Invoice",
    "entities": [
      {"entity": "CUSTOMER_NAME", "value": "Raju"},
      {"entity": "QUANTITY", "value": "4 packet"}
    ]
  },
  {
    "text": "Rakesh ko kal 2200 ka saman gaya invoice bana de",
    "intent": "Create_Invoice",
    "entities": [
      {"entity": "CUSTOMER_NAME", "value": "Rakesh"},
      {"entity": "AMOUNT", "value": "2200"},
      {"entity": "DATE_REFERENCE", "value": "kal"}
    ]
  },
  {
    "text": "875 ka bill generate karo Manoj",
    "intent": "Create_Invoice",
    "entities": [
      {"entity": "AMOUNT", "value": "875"},
      {"entity": "CUSTOMER_NAME", "value": "Manoj"}
    ]
  },
  {
    "text": "Amit ke liye naya invoice bana 3200 ka",
    "intent": "Create_Invoice",
    "entities": [
      {"entity": "CUSTOMER_NAME", "value": "Amit"},
      {"entity": "AMOUNT", "value": "3200"}
    ]
  },
  {
    "text": "600 ka saman diya tha uska bill bana",
    "intent": "Create_Invoice",
    "entities": [
      {"entity": "AMOUNT", "value": "600"}
    ]
  },
  {
    "text": "Ek invoice bana do 510 ka Rohit ke naam se",
    "intent": "Create_Invoice",
    "entities": [
      {"entity": "AMOUNT", "value": "510"},
      {"entity": "CUSTOMER_NAME", "value": "Rohit"}
    ]
  },
  {
    "text": "1500 ka bill create karo aur save karo",
    "intent": "Create_Invoice",
    "entities": [
      {"entity": "AMOUNT", "value": "1500"}
    ]
  },
  {
    "text": "Us customer ke liye 700 ka bill bana jo kal aaya tha",
    "intent": "Create_Invoice",
    "entities": [
      {"entity": "AMOUNT", "value": "700"},
      {"entity": "DATE_REFERENCE", "value": "kal"}
    ]
  },
  {
    "text": "Invoice create karo Suresh ke naam se",
    "intent": "Create_Invoice",
    "entities": [
      {"entity": "CUSTOMER_NAME", "value": "Suresh"}
    ]
  },
  {
    "text": "Verma Traders ke liye 5000 ka bill create karo",
    "intent": "Create_Invoice",
    "entities": [
      {"entity": "CUSTOMER_NAME", "value": "Verma Traders"},
      {"entity": "AMOUNT", "value": "5000"}
    ]
  },
  {
    "text": "Maa Durga Traders ko 3200 ka maal gaya invoice bana",
    "intent": "Create_Invoice",
    "entities": [
      {"entity": "CUSTOMER_NAME", "value": "Maa Durga Traders"},
      {"entity": "AMOUNT", "value": "3200"}
    ]
  },
  {
    "text": "Ritu Kirana Store ke naam se 1800 ka bill bana do",
    "intent": "Create_Invoice",
    "entities": [
      {"entity": "CUSTOMER_NAME", "value": "Ritu Kirana Store"},
      {"entity": "AMOUNT", "value": "1800"}
    ]
},
{
  "text": "Rahul ke udhaar mein 500 jod do",
  "intent": "Add_Credit",
  "entities": [
    {"entity": "CUSTOMER_NAME", "value": "Rahul"},
    {"entity": "AMOUNT", "value": "500"}
  ]
},
{
  "text": "Neha ke account mein 1200 add karo",
  "intent": "Add_Credit",
  "entities": [
    {"entity": "CUSTOMER_NAME", "value": "Neha"},
    {"entity": "AMOUNT", "value": "1200"}
  ]
},
{
  "text": "3000 aur chadha do Sharma ji pe",
  "intent": "Add_Credit",
  "entities": [
    {"entity": "CUSTOMER_NAME", "value": "Sharma ji"},
    {"entity": "AMOUNT", "value": "3000"}
  ]
},
{
  "text": "Lakshmi ke udhaar mein 900 jod do",
  "intent": "Add_Credit",
  "entities": [
    {"entity": "CUSTOMER_NAME", "value": "Lakshmi"},
    {"entity": "AMOUNT", "value": "900"}
  ]
},
{
  "text": "Khan Enterprises ke naam pe 2500 aur likh do",
  "intent": "Add_Credit",
  "entities": [
    {"entity": "CUSTOMER_NAME", "value": "Khan Enterprises"},
    {"entity": "AMOUNT", "value": "2500"}
  ]
},
{
  "text": "Manoj ke khate mein 750 daal do",
  "intent": "Add_Credit",
  "entities": [
    {"entity": "CUSTOMER_NAME", "value": "Manoj"},
    {"entity": "AMOUNT", "value": "750"}
  ]
},
{
  "text": "Sunita pe 1100 aur chadha do",
  "intent": "Add_Credit",
  "entities": [
    {"entity": "CUSTOMER_NAME", "value": "Sunita"},
    {"entity": "AMOUNT", "value": "1100"}
  ]
},
{
  "text": "450 aur add karo Ravi ke ledger mein",
  "intent": "Add_Credit",
  "entities": [
    {"entity": "CUSTOMER_NAME", "value": "Ravi"},
    {"entity": "AMOUNT", "value": "450"}
  ]
},
{
  "text": "Kal ka 700 bhi add kar do Mohit ko",
  "intent": "Add_Credit",
  "entities": [
    {"entity": "CUSTOMER_NAME", "value": "Mohit"},
    {"entity": "AMOUNT", "value": "700"},
    {"entity": "DATE_REFERENCE", "value": "kal"}
  ]
},
{
  "text": "Gupta ji ka udhaar 1400 badha do",
  "intent": "Add_Credit",
  "entities": [
    {"entity": "CUSTOMER_NAME", "value": "Gupta ji"},
    {"entity": "AMOUNT", "value": "1400"}
  ]
},
{
  "text": "Rahul ke khate mein 200 aur jod do",
  "intent": "Add_Credit",
  "entities": [
    {"entity": "CUSTOMER_NAME", "value": "Rahul"},
    {"entity": "AMOUNT", "value": "200"}
  ]
},
{
  "text": "Neha pe 1800 aur chadh gaya",
  "intent": "Add_Credit",
  "entities": [
    {"entity": "CUSTOMER_NAME", "value": "Neha"},
    {"entity": "AMOUNT", "value": "1800"}
  ]
},
{
  "text": "Sharma ji ka 600 aur badha do",
  "intent": "Add_Credit",
  "entities": [
    {"entity": "CUSTOMER_NAME", "value": "Sharma ji"},
    {"entity": "AMOUNT", "value": "600"}
  ]
},
{
  "text": "Lakshmi ke account mein aur 950 daal do",
  "intent": "Add_Credit",
  "entities": [
    {"entity": "CUSTOMER_NAME", "value": "Lakshmi"},
    {"entity": "AMOUNT", "value": "950"}
  ]
},
{
  "text": "Ravi ko 400 aur udhaar likh do",
  "intent": "Add_Credit",
  "entities": [
    {"entity": "CUSTOMER_NAME", "value": "Ravi"},
    {"entity": "AMOUNT", "value": "400"}
  ]
},
{
  "text": "Gupta ji pe 2200 aur chadha dena",
  "intent": "Add_Credit",
  "entities": [
    {"entity": "CUSTOMER_NAME", "value": "Gupta ji"},
    {"entity": "AMOUNT", "value": "2200"}
  ]
},
{
  "text": "Kal ka 1300 bhi uske khate mein add karo",
  "intent": "Add_Credit",
  "entities": [
    {"entity": "AMOUNT", "value": "1300"},
    {"entity": "DATE_REFERENCE", "value": "kal"}
  ]
},
{
  "text": "Manoj ka udhaar 500 aur badha do",
  "intent": "Add_Credit",
  "entities": [
    {"entity": "CUSTOMER_NAME", "value": "Manoj"},
    {"entity": "AMOUNT", "value": "500"}
  ]
},
{
  "text": "Sunita ke naam pe 750 aur daal do",
  "intent": "Add_Credit",
  "entities": [
    {"entity": "CUSTOMER_NAME", "value": "Sunita"},
    {"entity": "AMOUNT", "value": "750"}
  ]
},
{
  "text": "Maa Durga Traders ka 3000 aur likh do",
  "intent": "Add_Credit",
  "entities": [
    {"entity": "CUSTOMER_NAME", "value": "Maa Durga Traders"},
    {"entity": "AMOUNT", "value": "3000"}
  ]
},
{
  "text": "Usko 850 aur jod do",
  "intent": "Add_Credit",
  "entities": [
    {"entity": "AMOUNT", "value": "850"}
  ]
},
{
  "text": "Ritu Kirana Store ke khate mein 1700 aur daal do",
  "intent": "Add_Credit",
  "entities": [
    {"entity": "CUSTOMER_NAME", "value": "Ritu Kirana Store"},
    {"entity": "AMOUNT", "value": "1700"}
  ]
},
{
  "text": "Pichle hafte ka 900 bhi add kar do Mohit ko",
  "intent": "Add_Credit",
  "entities": [
    {"entity": "CUSTOMER_NAME", "value": "Mohit"},
    {"entity": "AMOUNT", "value": "900"},
    {"entity": "DATE_REFERENCE", "value": "pichle hafte"}
  ]
},
{
  "text": "Khan Enterprises pe 2600 aur chadha do",
  "intent": "Add_Credit",
  "entities": [
    {"entity": "CUSTOMER_NAME", "value": "Khan Enterprises"},
    {"entity": "AMOUNT", "value": "2600"}
  ]
},
{
  "text": "Aaj ka 1200 bhi uske account mein daal do",
  "intent": "Add_Credit",
  "entities": [
    {"entity": "AMOUNT", "value": "1200"},
    {"entity": "DATE_REFERENCE", "value": "aaj"}
  ]
},
{
  "text": "Rahul ne 500 ka payment kar diya",
  "intent": "Record_Payment",
  "entities": [
    {"entity": "CUSTOMER_NAME", "value": "Rahul"},
    {"entity": "AMOUNT", "value": "500"}
  ]
},
{
  "text": "Neha ne 1200 bhej diya",
  "intent": "Record_Payment",
  "entities": [
    {"entity": "CUSTOMER_NAME", "value": "Neha"},
    {"entity": "AMOUNT", "value": "1200"}
  ]
},
{
  "text": "Sharma ji ne 3000 transfer kiya",
  "intent": "Record_Payment",
  "entities": [
    {"entity": "CUSTOMER_NAME", "value": "Sharma ji"},
    {"entity": "AMOUNT", "value": "3000"}
  ]
},
{
  "text": "Lakshmi ka 800 mil gaya",
  "intent": "Record_Payment",
  "entities": [
    {"entity": "CUSTOMER_NAME", "value": "Lakshmi"},
    {"entity": "AMOUNT", "value": "800"}
  ]
},
{
  "text": "Gupta ji ne pura paisa de diya",
  "intent": "Record_Payment",
  "entities": [
    {"entity": "CUSTOMER_NAME", "value": "Gupta ji"},
    {"entity": "TRANSACTION_STATUS", "value": "FULL_PAYMENT"}
  ]
},
{
  "text": "Ravi ne aadha paisa diya",
  "intent": "Record_Payment",
  "entities": [
    {"entity": "CUSTOMER_NAME", "value": "Ravi"},
    {"entity": "TRANSACTION_STATUS", "value": "PARTIAL_PAYMENT"}
  ]
},
{
  "text": "Manoj ka 750 aa gaya",
  "intent": "Record_Payment",
  "entities": [
    {"entity": "CUSTOMER_NAME", "value": "Manoj"},
    {"entity": "AMOUNT", "value": "750"}
  ]
},
{
  "text": "Sunita ne 1500 UPI se bheja",
  "intent": "Record_Payment",
  "entities": [
    {"entity": "CUSTOMER_NAME", "value": "Sunita"},
    {"entity": "AMOUNT", "value": "1500"},
    {"entity": "PAYMENT_MODE", "value": "UPI"}
  ]
},
{
  "text": "Khan Enterprises ka payment receive ho gaya",
  "intent": "Record_Payment",
  "entities": [
    {"entity": "CUSTOMER_NAME", "value": "Khan Enterprises"}
  ]
},
{
  "text": "Ritu ne 2000 transfer kiya",
  "intent": "Record_Payment",
  "entities": [
    {"entity": "CUSTOMER_NAME", "value": "Ritu"},
    {"entity": "AMOUNT", "value": "2000"}
  ]
},
{
  "text": "Verma Traders ne 5000 clear kar diya",
  "intent": "Record_Payment",
  "entities": [
    {"entity": "CUSTOMER_NAME", "value": "Verma Traders"},
    {"entity": "AMOUNT", "value": "5000"}
  ]
},
{
  "text": "Pooja ka 900 mil gaya",
  "intent": "Record_Payment",
  "entities": [
    {"entity": "CUSTOMER_NAME", "value": "Pooja"},
    {"entity": "AMOUNT", "value": "900"}
  ]
},
{
  "text": "Amit ne 2500 cash diya",
  "intent": "Record_Payment",
  "entities": [
    {"entity": "CUSTOMER_NAME", "value": "Amit"},
    {"entity": "AMOUNT", "value": "2500"},
    {"entity": "PAYMENT_MODE", "value": "CASH"}
  ]
},
{
  "text": "Maa Durga Traders ne aadha payment kiya",
  "intent": "Record_Payment",
  "entities": [
    {"entity": "CUSTOMER_NAME", "value": "Maa Durga Traders"},
    {"entity": "TRANSACTION_STATUS", "value": "PARTIAL_PAYMENT"}
  ]
},
{
  "text": "Rakesh ka 1100 aa gaya",
  "intent": "Record_Payment",
  "entities": [
    {"entity": "CUSTOMER_NAME", "value": "Rakesh"},
    {"entity": "AMOUNT", "value": "1100"}
  ]
}
,
  {
    "text": "Suresh ne 1300 ka payment bheja",
    "intent": "Record_Payment",
    "entities": [
      {"entity": "CUSTOMER_NAME", "value": "Suresh"},
      {"entity": "AMOUNT", "value": "1300"}
    ]
  },
  {
    "text": "Received 750 from Rohit",
    "intent": "Record_Payment",
    "entities": [
      {"entity": "CUSTOMER_NAME", "value": "Rohit"},
      {"entity": "AMOUNT", "value": "750"}
    ]
  },
  {
    "text": "Parveen ne kal 400 bheja",
    "intent": "Record_Payment",
    "entities": [
      {"entity": "CUSTOMER_NAME", "value": "Parveen"},
      {"entity": "AMOUNT", "value": "400"},
      {"entity": "DATE_REFERENCE", "value": "kal"}
    ]
  },
  {
    "text": "Full payment from Ritu received",
    "intent": "Record_Payment",
    "entities": [
      {"entity": "CUSTOMER_NAME", "value": "Ritu"},
      {"entity": "TRANSACTION_STATUS", "value": "FULL_PAYMENT"}
    ]
  },
  {
    "text": "Partial payment 200 by Ankit",
    "intent": "Record_Payment",
    "entities": [
      {"entity": "CUSTOMER_NAME", "value": "Ankit"},
      {"entity": "AMOUNT", "value": "200"},
      {"entity": "TRANSACTION_STATUS", "value": "PARTIAL_PAYMENT"}
    ]
  },
  {
    "text": "Payment of 300 via NEFT from Gupta ji",
    "intent": "Record_Payment",
    "entities": [
      {"entity": "CUSTOMER_NAME", "value": "Gupta ji"},
      {"entity": "AMOUNT", "value": "300"},
      {"entity": "PAYMENT_MODE", "value": "NEFT"}
    ]
  },
  {
    "text": "Cash 1000 mil gaya Vikram",
    "intent": "Record_Payment",
    "entities": [
      {"entity": "CUSTOMER_NAME", "value": "Vikram"},
      {"entity": "AMOUNT", "value": "1000"},
      {"entity": "PAYMENT_MODE", "value": "CASH"}
    ]
  },
  {
    "text": "Khan Enterprises ne 1800 transfer kiya via bank",
    "intent": "Record_Payment",
    "entities": [
      {"entity": "CUSTOMER_NAME", "value": "Khan Enterprises"},
      {"entity": "AMOUNT", "value": "1800"},
      {"entity": "PAYMENT_MODE", "value": "BANK"}
    ]
  },
  {
    "text": "Aaj ka 450 payment aa gaya",
    "intent": "Record_Payment",
    "entities": [
      {"entity": "AMOUNT", "value": "450"},
      {"entity": "DATE_REFERENCE", "value": "aaj"}
    ]
  },
  {
    "text": "Customer paid 600",
    "intent": "Record_Payment",
    "entities": [
      {"entity": "AMOUNT", "value": "600"}
    ]
  },
  {
    "text": "Neha ne aadha 300 bheja",
    "intent": "Record_Payment",
    "entities": [
      {"entity": "CUSTOMER_NAME", "value": "Neha"},
      {"entity": "AMOUNT", "value": "300"},
      {"entity": "TRANSACTION_STATUS", "value": "PARTIAL_PAYMENT"}
    ]
  },
  {
    "text": "Invoice 123 paid 750 by Pooja",
    "intent": "Record_Payment",
    "entities": [
      {"entity": "CUSTOMER_NAME", "value": "Pooja"},
      {"entity": "AMOUNT", "value": "750"}
    ]
  }
]